README.md
setup.py
imis/__init__.py
imis/activity.py
imis/api.py
imis/demo.py
imis/iqa.py
imis/manager.py
imis/name_fin.py
imis/party.py
imis/record.py
imis/user.py
imis/utils.py
imis_projectweekend.egg-info/PKG-INFO
imis_projectweekend.egg-info/SOURCES.txt
imis_projectweekend.egg-info/dependency_links.txt
imis_projectweekend.egg-info/requires.txt
imis_projectweekend.egg-info/top_level.txt