Metadata-Version: 1.2
Name: imis-projectweekend
Version: 0.1.9
Summary: A Python client for the iMIS REST API
Home-page: https://github.com/projectweekend/imis
Author: Brian Hines
Author-email: brian@projectweekend.net
License: UNKNOWN
Platform: UNKNOWN
Classifier: Programming Language :: Python :: 3
Classifier: License :: OSI Approved :: MIT License
Classifier: Operating System :: OS Independent
Requires-Python: >=3.6
